{
  "scenarios": [
    {
      "role_id": "sales_intern",
      "role_name": "Стажер направление продаж и развития",
      "questions": [
        {
          "id": "sales_q1",
          "text": "Клиент говорит: 'Мне это не нужно, я и так всем доволен'. Твои действия?",
          "options": [
            "Скажу 'хорошо, до свидания' и завершу разговор",
            "Спрошу: 'А что именно вас устраивает? Может, есть что улучшить?'",
            "Начну агрессивно продавать, чтобы переубедить",
            "Предложу скидку, чтобы заинтересовать",
            "Свой вариант"
          ]
        },
        {
          "id": "sales_q2",
          "text": "У тебя 3 задачи: срочный звонок важному клиенту, подготовка отчёта к вечеру, встреча с командой через час. Что сделаешь первым?",
          "options": [
            "Сначала позвоню клиенту — это срочно",
            "Начну готовить отчёт, чтобы не забыть",
            "Пойду на встречу с командой, остальное потом",
            "Составлю план и расставлю приоритеты по важности",
            "Свой вариант"
          ]
        },
        {
          "id": "sales_q3",
          "text": "Тебе нужно проанализировать данные о продажах за последний квартал. С чего начнёшь?",
          "options": [
            "Сразу посчитаю средние показатели",
            "Соберу все данные, проверю на ошибки, потом сравню с прошлым периодом",
            "Попрошу коллегу сделать за меня",
            "Посмотрю только итоговые цифры",
            "Свой вариант"
          ]
        }
      ]
    },
    {
      "role_id": "hr_intern",
      "role_name": "Стажер HR",
      "questions": [
        {
          "id": "hr_q1",
          "text": "Ты ищешь кандидата на вакансию. У тебя 50 резюме за день. Как будешь действовать?",
          "options": [
            "Быстро просмотрю все и выберу первых попавшихся",
            "Составлю чек-лист ключевых требований и отфильтрую по нему",
            "Попрошу помощи у коллег",
            "Отложу на завтра",
            "Свой вариант"
          ]
        },
        {
          "id": "hr_q2",
          "text": "Кандидат опаздывает на собеседование на 15 минут без предупреждения. Твои действия?",
          "options": [
            "Откажу ему сразу — это неуважение",
            "Подожду и проведу собеседование, но сделаю пометку",
            "Позвоню и спрошу, в чём дело, решу на месте",
            "Перенесу на другой день",
            "Свой вариант"
          ]
        },
        {
          "id": "hr_q3",
          "text": "Какие инструменты ты используешь для поиска кандидатов?",
          "options": [
            "Только hh.ru",
            "hh.ru, LinkedIn, Telegram-каналы, рекомендации",
            "Попрошу HR-ов дать мне кандидатов",
            "Не знаю, буду искать в Google",
            "Свой вариант"
          ]
        }
      ]
    },
    {
      "role_id": "engineer_lks",
      "role_name": "Стажёр-инженер по эксплуатации линейно-кабельных сооружений",
      "questions": [
        {
          "id": "eng_q1",
          "text": "Тебе дали схему кабельной сети. Что ты будешь с ней делать?",
          "options": [
            "Посмотрю и отложу в сторону",
            "Проверю соответствие реальной сети, найду расхождения",
            "Перерисую красиво",
            "Отправлю начальнику",
            "Свой вариант"
          ]
        },
        {
          "id": "eng_q2",
          "text": "Оборудование на узле связи перестало работать. Твои первые шаги?",
          "options": [
            "Позвоню старшему инженеру",
            "Проверю логи, посмотрю индикаторы, попробую перезагрузить",
            "Пойду пить чай, пока само не починится",
            "Напишу заявку в техподдержку",
            "Свой вариант"
          ]
        },
        {
          "id": "eng_q3",
          "text": "Что для тебя значит 'любознательность и интерес к новому' в работе инженера?",
          "options": [
            "Читать новости про технологии",
            "Изучать новое оборудование, пробовать настраивать, задавать вопросы",
            "Ходить на курсы, потому что начальник заставляет",
            "Смотреть YouTube-каналы про IT",
            "Свой вариант"
          ]
        }
      ]
    },
    {
      "role_id": "lawyer",
      "role_name": "Юрист",
      "questions": [
        {
          "id": "law_q1",
          "text": "Сотрудника увольняют, он не согласен. Какие документы ты проверишь в первую очередь?",
          "options": [
            "Трудовой договор, приказ об увольнении, заявление сотрудника",
            "Ничего, HR сам разберётся",
            "Только трудовую книжку",
            "Личное дело и график отпусков",
            "Свой вариант"
          ]
        },
        {
          "id": "law_q2",
          "text": "Вышел новый закон о персональных данных. Что ты сделаешь?",
          "options": [
            "Прочитаю и забуду",
            "Изучу, проанализирую влияние на компанию, подготовлю рекомендации",
            "Отправлю ссылку коллегам",
            "Подожду, пока юрист-старший скажет, что делать",
            "Свой вариант"
          ]
        },
        {
          "id": "law_q3",
          "text": "HR просит рассчитать премию сотруднику. Твоя реакция?",
          "options": [
            "Скажу, что это не моя зона ответственности",
            "Проверю локальные акты, систему оплаты труда, дам заключение",
            "Рассчитаю сам",
            "Попрошу бухгалтерию",
            "Свой вариант"
          ]
        }
      ]
    },
    {
      "role_id": "procurement",
      "role_name": "Специалист по сопровождению закупок",
      "questions": [
        {
          "id": "proc_q1",
          "text": "Поставщик задерживает поставку. Твои действия?",
          "options": [
            "Напишу жалобу руководству",
            "Свяжусь с поставщиком, выясню причину, проверю договор",
            "Расторгну договор сразу",
            "Ничего, подожду",
            "Свой вариант"
          ]
        },
        {
          "id": "proc_q2",
          "text": "Что такое ERP-система и зачем она нужна в закупках?",
          "options": [
            "Не знаю",
            "Это программа для управления ресурсами предприятия, помогает отслеживать заказы, бюджеты, сроки",
            "База данных клиентов",
            "Программа для бухгалтерии",
            "Свой вариант"
          ]
        },
        {
          "id": "proc_q3",
          "text": "У тебя 3 контракта, все с разными сроками. Как не пропустить дедлайны?",
          "options": [
            "Буду держать в голове",
            "Заведу таблицу в Excel с датами и напоминаниями",
            "Попрошу секретаря напоминать",
            "Буду работать по одному контракту, остальные потом",
            "Свой вариант"
          ]
        }
      ]
    },
    {
      "role_id": "marketing",
      "role_name": "Маркетинг",
      "questions": [
        {
          "id": "mkt_q1",
          "text": "Как ты оценишь эффективность рекламной кампании?",
          "options": [
            "По количеству лайков в соцсетях",
            "По ROI, конверсии, охватам, стоимости лида",
            "Спрошу у начальника",
            "По тому, сколько людей увидели рекламу",
            "Свой вариант"
          ]
        },
        {
          "id": "mkt_q2",
          "text": "Конкуренты запустили агрессивную рекламную кампанию. Что сделаешь?",
          "options": [
            "Ничего, пусть делают",
            "Проанализирую их акцию, сделаю выводы, предложу контрмеры",
            "Скопирую их рекламу",
            "Снижу цены",
            "Свой вариант"
          ]
        },
        {
          "id": "mkt_q3",
          "text": "Что такое BTL-мероприятия? Приведи пример.",
          "options": [
            "Не знаю",
            "Промо-акции, дегустации, раздача листовок — например, консультант в ТЦ",
            "Реклама на ТВ",
            "Контекстная реклама в Яндексе",
            "Свой вариант"
          ]
        }
      ]
    },
    {
      "role_id": "property_manager",
      "role_name": "Менеджер отдела недвижимости и эксплуатации зданий",
      "questions": [
        {
          "id": "prop_q1",
          "text": "В офисе сломалась система кондиционирования в жару. Твои действия?",
          "options": [
            "Позвоню в УК и буду ждать",
            "Оценю ситуацию, оформлю заявку подрядчику, найду временное решение",
            "Открою окна",
            "Ничего, пусть сотрудники терпят",
            "Свой вариант"
          ]
        },
        {
          "id": "prop_q2",
          "text": "Подрядчик сделал ремонт, но качество плохое. Что будешь делать?",
          "options": [
            "Подпишу акт, чтобы не ругаться",
            "Проверю по договору, составлю дефектную ведомость, потребую переделать",
            "Позвоню и поругаюсь",
            "Найму другого",
            "Свой вариант"
          ]
        },
        {
          "id": "prop_q3",
          "text": "Какие программы нужны для учёта материальных ценностей?",
          "options": [
            "Блокнот и ручка",
            "Excel, 1С, Oracle",
            "Не знаю",
            "Только Word",
            "Свой вариант"
          ]
        }
      ]
    },
    {
      "role_id": "transport",
      "role_name": "Ведущий специалист по транспортному обслуживанию",
      "questions": [
        {
          "id": "trans_q1",
          "text": "Водитель сообщает, что машина странно стучит. Твои действия?",
          "options": [
            "Скажу 'езжай дальше, потом посмотрим'",
            "Организую внеплановый техосмотр, запишу на диагностику",
            "Вызову эвакуатор",
            "Попрошу водителя самому разобраться",
            "Свой вариант"
          ]
        },
        {
          "id": "trans_q2",
          "text": "Как ты планируешь график ТО для 10 машин?",
          "options": [
            "Буду вспоминать когда кому надо",
            "Создам таблицу с пробегом и датами, поставлю напоминания",
            "Отдам механику",
            "Делаю ТО всем сразу раз в год",
            "Свой вариант"
          ]
        },
        {
          "id": "trans_q3",
          "text": "Сотруднику срочно нужна машина, но все заняты. Что сделаешь?",
          "options": [
            "Скажу 'нет машин'",
            "Посмотрю, можно ли освободить ближайшую, предложу такси как альтернативу",
            "Отменю чью-то поездку",
            "Не мои проблемы",
            "Свой вариант"
          ]
        }
      ]
    },
    {
      "role_id": "corporate_client",
      "role_name": "Специалист по работе с корпоративными клиентами",
      "questions": [
        {
          "id": "corp_q1",
          "text": "Корпоративный клиент звонит и кричит, что за услугу списали лишние деньги. Твои действия?",
          "options": [
            "Извинюсь и положу трубку",
            "Спокойно выслушаю, проверю историю платежей, объясню ситуацию",
            "Скажу, что это не моя проблема",
            "Переведу на другого специалиста",
            "Свой вариант"
          ]
        },
        {
          "id": "corp_q2",
          "text": "Клиент спрашивает: 'Какой тариф мне лучше выбрать для 50 сотрудников?' Что ответишь?",
          "options": [
            "Дам ссылку на сайт",
            "Спрошу про потребности, бюджет, активность, предложу 2-3 варианта с обоснованием",
            "Скажу 'самый дорогой'",
            "Не знаю",
            "Свой вариант"
          ]
        },
        {
          "id": "corp_q3",
          "text": "Как ты будешь выстраивать долгосрочные отношения с клиентом?",
          "options": [
            "Никак, он сам вернётся",
            "Буду периодически интересоваться делами, предлагать акции, решать проблемы быстро",
            "Поздравлю с Новым годом",
            "Буду звонить каждый день",
            "Свой вариант"
          ]
        }
      ]
    },
    {
      "role_id": "ai_analyst",
      "role_name": "Аналитик по внедрению AI",
      "questions": [
        {
          "id": "ai_q1",
          "text": "Как бы ты оценил финансовый эффект от внедрения чат-бота в поддержку?",
          "options": [
            "Не знаю, это сложно",
            "Сравню затраты на разработку с экономией на операторах, посчитаю ROI",
            "Спрошу у начальника",
            "Посмотрю, сколько запросов обработал бот",
            "Свой вариант"
          ]
        },
        {
          "id": "ai_q2",
          "text": "Какие инструменты анализа данных ты знаешь?",
          "options": [
            "Только Excel",
            "Python, SQL, BI-системы (Power BI, Tableau), Pandas",
            "Никаких",
            "Photoshop",
            "Свой вариант"
          ]
        },
        {
          "id": "ai_q3",
          "text": "У тебя есть 10 идей по применению ИИ. Как выбрать лучшую?",
          "options": [
            "Выберу наугад",
            "Оценю каждую по потенциальному эффекту, сложности, срокам, сделаю ранжирование",
            "Пусть команда голосует",
            "Сделаю всё сразу",
            "Свой вариант"
          ]
        }
      ]
    },
    {
      "role_id": "it_support",
      "role_name": "Направление сопровождения рабочих мест",
      "questions": [
        {
          "id": "it_q1",
          "text": "У пользователя не работает принтер. Что будешь делать?",
          "options": [
            "Скажу 'перезагрузите' и уйду",
            "Проверю очередь печати, драйверы, подключение, службы",
            "Позвоню в сервисный центр",
            "Куплю новый",
            "Свой вариант"
          ]
        },
        {
          "id": "it_q2",
          "text": "Что такое TCP/IP и зачем он нужен?",
          "options": [
            "Не знаю",
            "Это набор протоколов для передачи данных в сети, основа интернета",
            "Антивирус",
            "Программа для Windows",
            "Свой вариант"
          ]
        },
        {
          "id": "it_q3",
          "text": "Пользователь жалуется на медленный компьютер. Твои действия?",
          "options": [
            "Скажу 'купите новый'",
            "Посмотрю загрузку CPU, память, автозагрузку, проверить на вирусы",
            "Переустановлю Windows сразу",
            "Ничего, это норма",
            "Свой вариант"
          ]
        }
      ]
    },
    {
      "role_id": "seller",
      "role_name": "Продавец (Розничная сеть МТС)",
      "questions": [
        {
          "id": "seller_q1",
          "text": "В салон заходит клиент, который 'просто посмотреть'. Твои действия?",
          "options": [
            "Не буду подходить, пусть смотрит",
            "Поздороваюсь, спрошу 'что ищете?', расскажу про новинки",
            "Сразу начну продавать самый дорогой телефон",
            "Скажу 'обращайтесь если что' и уйду",
            "Свой вариант"
          ]
        },
        {
          "id": "seller_q2",
          "text": "Клиент говорит: 'У конкурентов дешевле на 2000 рублей'. Что ответишь?",
          "options": [
            "Ну и идите к конкурентам",
            "Соглашусь, что дешевле, но объясню преимущества (гарантия, обслуживание, бонусы)",
            "Сделаю скидку 2000 рублей",
            "Скажу, что это невозможно",
            "Свой вариант"
          ]
        },
        {
          "id": "seller_q3",
          "text": "Что для тебя 'интерес к digital технологиям'?",
          "options": [
            "Смотрю обзоры на YouTube",
            "Слежу за новинками, пробую новые гаджеты, разбираюсь в характеристиках",
            "Играю в компьютерные игры",
            "Ничего не понимаю в этом",
            "Свой вариант"
          ]
        }
      ]
    },
    {
      "role_id": "admin_support",
      "role_name": "Специалист по административно-хозяйственному обеспечению",
      "questions": [
        {
          "id": "admin_q1",
          "text": "В офисе прорвало трубу. Твои действия?",
          "options": [
            "Позвоню начальнику",
            "Перекрою воду, вызову аварийную службу, организую уборку",
            "Пойду домой",
            "Ничего, само пройдёт",
            "Свой вариант"
          ]
        },
        {
          "id": "admin_q2",
          "text": "Нужно организовать рабочее место для нового сотрудника. С чего начнёшь?",
          "options": [
            "Дам стол и стул",
            "Подберу мебель, компьютер, канцелярию, проверю освещение и розетки",
            "Пусть сам приносит",
            "Попрошу HR помочь",
            "Свой вариант"
          ]
        },
        {
          "id": "admin_q3",
          "text": "Как ведёшь учёт материальных ценностей?",
          "options": [
            "В голове",
            "В Excel/1С/Oracle: приход, списание, инвентаризация",
            "В блокноте",
            "Никак",
            "Свой вариант"
          ]
        }
      ]
    }
  ]
}